{
  "course": "discrete_math",
  "chunk_count": 20,
  "question_count": 20,
  "strategies": {
    "naive_top_k": {
      "answer_similarity": 0.5964,
      "context_precision": 0.8875,
      "context_recall": 0.995,
      "citation_accuracy": 1.0
    },
    "mmr": {
      "answer_similarity": 0.6033,
      "context_precision": 0.9,
      "context_recall": 1.0,
      "citation_accuracy": 1.0
    },
    "mmr_tier_boost": {
      "answer_similarity": 0.5931,
      "context_precision": 0.875,
      "context_recall": 0.995,
      "citation_accuracy": 1.0
    }
  }
}
